Topsis_Chhavi_102103605/Topsis.py
Topsis_Chhavi_102103605/__init__.py
Topsis_Chhavi_102103605-0.1.dist-info/LICENSE.txt
Topsis_Chhavi_102103605-0.1.dist-info/METADATA
Topsis_Chhavi_102103605-0.1.dist-info/WHEEL
Topsis_Chhavi_102103605-0.1.dist-info/top_level.txt
Topsis_Chhavi_102103605-0.1.dist-info/RECORD
